cytocluster/__init__.py
cytocluster/base.py
cytocluster/ensemble.py
cytocluster/methods/__init__.py
cytocluster/methods/consensus_k.py
cytocluster/methods/flowgrid.py
cytocluster/methods/flowsom.py
cytocluster/methods/latent.py
cytocluster/methods/parc.py
cytocluster/methods/pg.py
cytocluster/methods/spade.py
cytocluster/methods/utils.py
cytocluster/methods/wrapper.py
cytocluster/metrics.py
cytocluster/plotting.py
cytocluster/single.py
cytocluster/tests/__init__.py
cytocluster/tests/test_cluster_methods.py
cytocluster-0.1.13.dist-info/LICENSE
cytocluster-0.1.13.dist-info/WHEEL
cytocluster-0.1.13.dist-info/METADATA
cytocluster-0.1.13.dist-info/RECORD
